cliauth/__init__.py
cliauth-0.2.0.dist-info/LICENSE
cliauth-0.2.0.dist-info/METADATA
cliauth-0.2.0.dist-info/WHEEL
cliauth-0.2.0.dist-info/top_level.txt
cliauth-0.2.0.dist-info/RECORD
