Metadata-Version: 2.1
Name: cliauth
Version: 0.2.0
Summary: Easy auth for your python CLI
Home-page: UNKNOWN
License: UNKNOWN
Platform: UNKNOWN
Requires-Python: >=3
Requires-Dist: requests
Requires-Dist: pyjwt
